is_sorted.py
is_sorted-0.0.2.dist-info/LICENSE
is_sorted-0.0.2.dist-info/METADATA
is_sorted-0.0.2.dist-info/WHEEL
is_sorted-0.0.2.dist-info/top_level.txt
is_sorted-0.0.2.dist-info/RECORD
