Metadata-Version: 2.1
Name: is-sorted
Version: 0.0.2
Summary: tool to check sorting
Home-page: https://github.com/vonafor/is_sorted
Author: Yan Mitrofanov
Author-email: mmxlviii@mail.ru
License: MIT License
Platform: UNKNOWN
Classifier: Programming Language :: Python :: 3
Classifier: License :: OSI Approved :: MIT License
Classifier: Operating System :: OS Independent
Requires-Python: >=3.5
Provides-Extra: tests
Requires-Dist: pytest (>=5.3.2) ; extra == 'tests'
